read_aconity_layers-0.4.10.dist-info/METADATA
read_aconity_layers-0.4.10.dist-info/WHEEL
read_aconity_layers-0.4.10.dist-info/licenses/LICENSE
read_aconity_layers/__init__.py
read_aconity_layers/read_aconity_layers.cpython-313t-i386-linux-gnu.so
read_aconity_layers-0.4.10.dist-info/RECORD
